geodata_harvester/__init__.py
geodata_harvester/arc2meter.py
geodata_harvester/getdata_dea.py
geodata_harvester/getdata_dem.py
geodata_harvester/getdata_ee.py
geodata_harvester/getdata_landscape.py
geodata_harvester/getdata_radiometric.py
geodata_harvester/getdata_silo.py
geodata_harvester/getdata_slga.py
geodata_harvester/harvest.py
geodata_harvester/settingshandler.py
geodata_harvester/spatial.py
geodata_harvester/temporal.py
geodata_harvester/utils.py
geodata_harvester/validate_settings.py
geodata_harvester/write_logs.py
geodata_harvester/widgets/__init__.py
geodata_harvester/widgets/harvesterwidgets.py
geodata_harvester/widgets/ipywidgets_file_selector.py
geodata_harvester/widgets/ipyfilechooser/__init__.py
geodata_harvester/widgets/ipyfilechooser/errors.py
geodata_harvester/widgets/ipyfilechooser/filechooser.py
geodata_harvester/widgets/ipyfilechooser/utils.py
geodata_harvester-0.0.2.dist-info/METADATA
geodata_harvester-0.0.2.dist-info/WHEEL
geodata_harvester-0.0.2.dist-info/top_level.txt
geodata_harvester-0.0.2.dist-info/RECORD
