Metadata-Version: 2.1
Name: geodata-harvester
Version: 0.0.2
Summary: An automation tool for harvesting and processing geodata from the web
Home-page: https://github.com/Sydney-Informatics-Hub/geodata-harvester
License: LGPL-3.0
Classifier: Programming Language :: Python :: 3
Classifier: Operating System :: OS Independent
Requires-Python: >=3.9
Requires-Dist: numpy
Requires-Dist: rasterio
Requires-Dist: termcolor
Requires-Dist: xarray
Requires-Dist: matplotlib
Requires-Dist: alive-progress (>=3.0.1)
Requires-Dist: owslib (==0.27.2)
Requires-Dist: netCDF4
Requires-Dist: rioxarray
Requires-Dist: pyyaml
Requires-Dist: pandas
Requires-Dist: geopandas
Requires-Dist: pyproj
Requires-Dist: numba
Requires-Dist: shapely
Requires-Dist: fiona (>=1.8.21)
Requires-Dist: ipywidgets (>=7.6.5)
Requires-Dist: ipython
Requires-Dist: eeharvest
Requires-Dist: schema
Requires-Dist: requests (==2.28.1)
